giotto_bottleneck.cp35-win_amd64.pyd
giotto_cubical_complex.cp35-win_amd64.pyd
giotto_persistent_cohomology.cp35-win_amd64.pyd
giotto_ripser.cp35-win_amd64.pyd
giotto_simplex_tree.cp35-win_amd64.pyd
giotto_wasserstein.cp35-win_amd64.pyd
giotto/__init__.py
giotto/_version.py
giotto/base.py
giotto/pipeline.py
giotto/diagrams/__init__.py
giotto/diagrams/_metrics.py
giotto/diagrams/_utils.py
giotto/diagrams/distance.py
giotto/diagrams/features.py
giotto/diagrams/preprocessing.py
giotto/diagrams/tests/__init__.py
giotto/diagrams/tests/test_distance.py
giotto/diagrams/tests/test_features.py
giotto/diagrams/tests/test_preprocessing.py
giotto/externals/__init__.py
giotto/externals/python/__init__.py
giotto/externals/python/cubical_complex_interface.py
giotto/externals/python/ripser_interface.py
giotto/externals/python/simplex_tree_interface.py
giotto/graphs/__init__.py
giotto/graphs/geodesic_distance.py
giotto/graphs/kneighbors.py
giotto/graphs/transition.py
giotto/graphs/tests/__init__.py
giotto/graphs/tests/test_geodesic_distance.py
giotto/graphs/tests/test_kneighbors.py
giotto/graphs/tests/test_transition.py
giotto/homology/__init__.py
giotto/homology/_utils.py
giotto/homology/consistent.py
giotto/homology/point_clouds.py
giotto/homology/tests/__init__.py
giotto/homology/tests/test_consistent.py
giotto/homology/tests/test_point_clouds.py
giotto/meta_transformers/__init__.py
giotto/meta_transformers/features.py
giotto/meta_transformers/tests/__init__.py
giotto/meta_transformers/tests/test_features.py
giotto/tests/__init__.py
giotto/tests/test_pipeline.py
giotto/time_series/__init__.py
giotto/time_series/embedding.py
giotto/time_series/features.py
giotto/time_series/multivariate.py
giotto/time_series/preprocessing.py
giotto/time_series/target.py
giotto/time_series/tests/__init__.py
giotto/time_series/tests/test_embedding.py
giotto/time_series/tests/test_multivariate.py
giotto/time_series/tests/test_preprocessing.py
giotto/utils/__init__.py
giotto/utils/testing.py
giotto_learn-0.1.3.post1.dist-info/LICENSE
giotto_learn-0.1.3.post1.dist-info/METADATA
giotto_learn-0.1.3.post1.dist-info/WHEEL
giotto_learn-0.1.3.post1.dist-info/top_level.txt
giotto_learn-0.1.3.post1.dist-info/RECORD
