Metadata-Version: 2.1
Name: giotto-learn
Version: 0.1.3.post1
Summary: Toolbox for Machine Learning using Topological Data Analysis.
Home-page: https://github.com/giotto-learn/giotto-learn
Maintainer: Guillaume Tauzin
Maintainer-email: maintainers@giotto.ai
License: Apache 2.0
Download-URL: https://github.com/giotto-learn/giotto-learn/tarball/v0.1.3-r1
Keywords: machine learning topological data analysis persistent homology,persistence diagrams
Platform: UNKNOWN
Classifier: Intended Audience :: Science/Research
Classifier: Intended Audience :: Developers
Classifier: License :: OSI Approved
Classifier: Programming Language :: C
Classifier: Programming Language :: Python
Classifier: Topic :: Software Development
Classifier: Topic :: Scientific/Engineering
Classifier: Operating System :: Microsoft :: Windows
Classifier: Operating System :: POSIX
Classifier: Operating System :: Unix
Classifier: Operating System :: MacOS
Classifier: Programming Language :: Python :: 3.5
Classifier: Programming Language :: Python :: 3.6
Classifier: Programming Language :: Python :: 3.7
Provides-Extra: doc
Provides-Extra: tests
Provides-Extra: examples
Requires-Dist: numpy (>=1.17.0)
Requires-Dist: scipy (>=0.17.0)
Requires-Dist: scikit-learn (>=0.21.3)
Requires-Dist: joblib (>=0.11)
Provides-Extra: doc
Requires-Dist: sphinx; extra == 'doc'
Requires-Dist: sphinx-gallery; extra == 'doc'
Requires-Dist: sphinx-issues; extra == 'doc'
Requires-Dist: sphinx-rtd-theme; extra == 'doc'
Requires-Dist: numpydoc; extra == 'doc'
Provides-Extra: examples
Requires-Dist: jupyter; extra == 'examples'
Requires-Dist: matplotlib; extra == 'examples'
Requires-Dist: plotly; extra == 'examples'
Provides-Extra: tests
Requires-Dist: pytest; extra == 'tests'
Requires-Dist: pytest-cov; extra == 'tests'
Requires-Dist: pytest-azurepipelines; extra == 'tests'
Requires-Dist: pytest-benchmark; extra == 'tests'
Requires-Dist: jupyter-contrib-nbextensions; extra == 'tests'
Requires-Dist: flake8; extra == 'tests'
